PyTomasUtils/__init__.py
pytomasutils-1.0.8.dist-info/METADATA
pytomasutils-1.0.8.dist-info/WHEEL
pytomasutils-1.0.8.dist-info/licenses/LICENSE
pytomasutils-1.0.8.dist-info/RECORD
